odoo9_addon_web_widget_bokeh_chart-9.0.1.0.0.99.dev3-nspkg.pth
odoo_addons/web_widget_bokeh_chart/README.rst
odoo_addons/web_widget_bokeh_chart/__init__.py
odoo_addons/web_widget_bokeh_chart/__openerp__.py
odoo_addons/web_widget_bokeh_chart/static/description/example.png
odoo_addons/web_widget_bokeh_chart/static/description/icon.png
odoo_addons/web_widget_bokeh_chart/static/src/js/web_widget_bokeh_chart.js
odoo_addons/web_widget_bokeh_chart/static/src/lib/bokeh/bokeh-0.12.7.css
odoo_addons/web_widget_bokeh_chart/static/src/lib/bokeh/bokeh-0.12.7.js
odoo_addons/web_widget_bokeh_chart/static/src/lib/bokeh/bokeh-widgets-0.12.7.css
odoo_addons/web_widget_bokeh_chart/static/src/lib/bokeh/bokeh-widgets-0.12.7.js
odoo_addons/web_widget_bokeh_chart/views/web_widget_bokeh_chart.xml
odoo9_addon_web_widget_bokeh_chart-9.0.1.0.0.99.dev3.dist-info/METADATA
odoo9_addon_web_widget_bokeh_chart-9.0.1.0.0.99.dev3.dist-info/WHEEL
odoo9_addon_web_widget_bokeh_chart-9.0.1.0.0.99.dev3.dist-info/namespace_packages.txt
odoo9_addon_web_widget_bokeh_chart-9.0.1.0.0.99.dev3.dist-info/top_level.txt
odoo9_addon_web_widget_bokeh_chart-9.0.1.0.0.99.dev3.dist-info/RECORD
