Metadata-Version: 2.1
Name: odoo9-addon-web-widget-bokeh-chart
Version: 9.0.1.0.0.99.dev3
Summary: This widget allows to display charts using Bokeh library.
Home-page: https://github.com/OCA/web
Author: Eficent, Odoo Community Association (OCA)
Author-email: support@odoo-community.org
License: AGPL-3
Platform: UNKNOWN
Classifier: Programming Language :: Python
Classifier: Framework :: Odoo
Classifier: License :: OSI Approved :: GNU Affero General Public License v3
Requires-Python: ~=2.7
Requires-Dist: bokeh
Requires-Dist: odoo (<9.1a,>=9.0a)
